api_machine/__init__.py
api_machine/cli.py
api_machine/entity.py
api_machine/events.py
api_machine/exc.py
api_machine/lifecycle.py
api_machine/pubsub.py
api_machine/python_api_machine.py
api_machine/schema.py
api_machine/service.py
api_machine/storage/__init__.py
api_machine/storage/dynamodb.py
python_api_machine-0.11.1.dist-info/AUTHORS.rst
python_api_machine-0.11.1.dist-info/LICENSE
python_api_machine-0.11.1.dist-info/METADATA
python_api_machine-0.11.1.dist-info/WHEEL
python_api_machine-0.11.1.dist-info/entry_points.txt
python_api_machine-0.11.1.dist-info/top_level.txt
python_api_machine-0.11.1.dist-info/RECORD
