Metadata-Version: 2.1
Name: python-api-machine
Version: 0.11.1
Summary: Create APIs by combining models and state machines
Home-page: https://github.com/itsallcode-nl/python_api_machine
Author: Martijn Meijer
Author-email: tech@itsallcode.nl
License: MIT license
Keywords: python_api_machine
Classifier: Development Status :: 2 - Pre-Alpha
Classifier: Intended Audience :: Developers
Classifier: License :: OSI Approved :: MIT License
Classifier: Natural Language :: English
Classifier: Programming Language :: Python :: 3
Classifier: Programming Language :: Python :: 3.6
Classifier: Programming Language :: Python :: 3.7
Classifier: Programming Language :: Python :: 3.8
Requires-Python: >=3.6
License-File: LICENSE
License-File: AUTHORS.rst
Requires-Dist: Click >=7.0
Requires-Dist: boto3
Requires-Dist: pydantic >1.8.0
